odoo8_addon_l10n_eu_oss-8.0.1.1.0.99.dev2-py3.8-nspkg.pth
odoo_addons/l10n_eu_oss/README.rst
odoo_addons/l10n_eu_oss/__init__.py
odoo_addons/l10n_eu_oss/__openerp__.py
odoo_addons/l10n_eu_oss/data/oss.tax.rate.csv
odoo_addons/l10n_eu_oss/i18n/l10n_eu_oss.pot
odoo_addons/l10n_eu_oss/migrations/8.0.1.1.0/post-migration.py
odoo_addons/l10n_eu_oss/models/__init__.py
odoo_addons/l10n_eu_oss/models/account_tax.py
odoo_addons/l10n_eu_oss/models/oss_tax_rate.py
odoo_addons/l10n_eu_oss/readme/CONFIGURE.rst
odoo_addons/l10n_eu_oss/readme/CONTRIBUTORS.rst
odoo_addons/l10n_eu_oss/readme/DESCRIPTION.rst
odoo_addons/l10n_eu_oss/readme/ROADMAP.rst
odoo_addons/l10n_eu_oss/readme/USAGE.rst
odoo_addons/l10n_eu_oss/security/ir.model.access.csv
odoo_addons/l10n_eu_oss/static/description/icon.png
odoo_addons/l10n_eu_oss/static/description/index.html
odoo_addons/l10n_eu_oss/tests/__init__.py
odoo_addons/l10n_eu_oss/tests/test_l10n_eu_oss.py
odoo_addons/l10n_eu_oss/views/res_config_settings.xml
odoo_addons/l10n_eu_oss/wizard/__init__.py
odoo_addons/l10n_eu_oss/wizard/l10n_eu_oss_wizard.py
odoo_addons/l10n_eu_oss/wizard/l10n_eu_oss_wizard.xml
odoo8_addon_l10n_eu_oss-8.0.1.1.0.99.dev2.dist-info/METADATA
odoo8_addon_l10n_eu_oss-8.0.1.1.0.99.dev2.dist-info/WHEEL
odoo8_addon_l10n_eu_oss-8.0.1.1.0.99.dev2.dist-info/namespace_packages.txt
odoo8_addon_l10n_eu_oss-8.0.1.1.0.99.dev2.dist-info/top_level.txt
odoo8_addon_l10n_eu_oss-8.0.1.1.0.99.dev2.dist-info/RECORD
